watcher/__init__.py
watcher/watcher.py
ACU-0.2.1.dist-info/LICENSE
ACU-0.2.1.dist-info/METADATA
ACU-0.2.1.dist-info/WHEEL
ACU-0.2.1.dist-info/entry_points.txt
ACU-0.2.1.dist-info/top_level.txt
ACU-0.2.1.dist-info/RECORD
